dnxsso/__init__.py
dnxsso/__main__.py
dnxsso/cli.py
dnxsso-0.5.0.dist-info/LICENSE
dnxsso-0.5.0.dist-info/METADATA
dnxsso-0.5.0.dist-info/WHEEL
dnxsso-0.5.0.dist-info/entry_points.txt
dnxsso-0.5.0.dist-info/top_level.txt
dnxsso-0.5.0.dist-info/RECORD
