Metadata-Version: 2.1
Name: dnxsso
Version: 0.5.0
Summary: Sync up AWS CLI v2 SSO login session to legacy CLI v1 credentials
Home-page: https://github.com/DNXLabs/dnxsso
Author: DNX Solutions
Author-email: contact@dnx.solutions
License: MIT
Platform: UNKNOWN
Provides-Extra: dev
Requires-Dist: twine ; extra == 'dev'
Requires-Dist: setuptools ; extra == 'dev'
Requires-Dist: wheel ; extra == 'dev'
Provides-Extra: test
Requires-Dist: pytest ; extra == 'test'
Requires-Dist: pytest-cov ; extra == 'test'
Requires-Dist: flake8 ; extra == 'test'
Requires-Dist: mockito ; extra == 'test'
Requires-Dist: cli-test-helpers ; extra == 'test'
Requires-Dist: nose2 ; extra == 'test'
Requires-Dist: coveralls ; extra == 'test'
